{"repo": {"timestamp": 1691496141000, "version": 20002, "name": "LUKYMAS repository", "icon": "repoicon.png", "address": "https://raw.githubusercontent.com/lksmasin/fdroidrepo/main/fdroid/repo", "description": "LUKYMAS F-Droid repository for apps", "mirrors": ["https://raw.githubusercontent.com/lksmasin/fdroidrepo/master/fdroid/repo"]}, "requests": {"install": [], "uninstall": []}, "apps": [{"authorEmail": "mail@lukymas.eu.org", "authorName": "LUKYMAS", "categories": ["Internet"], "suggestedVersionCode": "2147483647", "description": "Po\u010das\u00ed s p\u0159edpov\u011bd\u00ed od n\u011bkolika poskitovale\u016f a s d\u016frazem na vzhled.\nMaterial you vzhled, upozorn\u011bn\u00ed na p\u0159eh\u00e1\u0148ky, widgety.. a v\u00edce!", "issueTracker": "https://github.com/lksmasin/climasense/issues", "license": "LGPL-3.0", "name": "ClimaSense", "sourceCode": "https://github.com/lksmasin/climasense", "summary": "Po\u010das\u00ed s p\u0159edpov\u011bd\u00ed od v\u00edce poskytovatel\u016f a p\u011bkn\u00fdm vzhedem.", "webSite": "https://github.com/lksmasin/climasense", "added": 1691179198000, "packageName": "org.climasense", "lastUpdated": 1691179198000, "localized": {"cs": {"icon": "icon_9ldJ3pshJFInkSwazEJUcxxU0c9qlqX4_odB-MnMUPI=.png", "phoneScreenshots": ["Screenshot_1.png", "Screenshot_2.png", "Screenshot_3.png"]}}}], "packages": {"org.climasense": [{"added": 1691179198000, "apkName": "climasense.apk", "features": ["android.software.live_wallpaper", "android.hardware.location.gps", "android.hardware.location.network"], "hash": "dd25a65932906fc71f147d331b25636928408fb9410541f3f44bce7b7142a44b", "hashType": "sha256", "minSdkVersion": 21, "nativecode": ["arm64-v8a", "armeabi-v7a", "x86", "x86_64"], "packageName": "org.climasense", "sig": "bfdf3d34923bc476ce8f75eed73cd0bd", "signer": "67b67c88ee2ce426d539ed0eddbb507c74bcab3d651ce069b0113f7e14fe97e7", "size": 11091452, "targetSdkVersion": 33, "uses-permission": [["android.permission.ACCESS_FINE_LOCATION", null], ["android.permission.ACCESS_COARSE_LOCATION", null], ["android.permission.ACCESS_BACKGROUND_LOCATION", null], ["android.permission.READ_EXTERNAL_STORAGE", null], ["android.permission.FOREGROUND_SERVICE", null], ["android.permission.REQUEST_IGNORE_BATTERY_OPTIMIZATIONS", null], ["android.permission.ACCESS_NETWORK_STATE", null], ["android.permission.ACCESS_WIFI_STATE", null], ["android.permission.INTERNET", null], ["android.permission.RECEIVE_BOOT_COMPLETED", null], ["com.android.alarm.permission.SET_ALARM", null], ["android.permission.EXPAND_STATUS_BAR", null], ["android.permission.POST_NOTIFICATIONS", null], ["android.permission.WAKE_LOCK", null], ["org.climasense.DYNAMIC_RECEIVER_NOT_EXPORTED_PERMISSION", null]], "versionCode": 2, "versionName": "1"}]}}